README
setup.py
py_retain.egg-info/PKG-INFO
py_retain.egg-info/SOURCES.txt
py_retain.egg-info/dependency_links.txt
py_retain.egg-info/not-zip-safe
py_retain.egg-info/requires.txt
py_retain.egg-info/top_level.txt
retain/__init__.py
retain/retain.py
tests/__init__.py