Metadata-Version: 1.0
Name: py-retain
Version: 0.1.0
Summary: Retcin.cc API wrapper
Home-page: http://github.com/retaincc/py-retain
Author: Rick Mak
Author-email: rick.mak@gmail
License: MIT License
Keywords: Retaincc Reainc python
Platform: UNKNOWN
